graphyne/Condition.py
graphyne/Exceptions.py
graphyne/Fileutils.py
graphyne/Graph.py
graphyne/Logger.py
graphyne/Numeric.py
graphyne/Scripting.py
graphyne/Scripts.py
graphyne/__init__.py
graphyne-1.2.2.dist-info/LICENSE
graphyne-1.2.2.dist-info/METADATA
graphyne-1.2.2.dist-info/WHEEL
graphyne-1.2.2.dist-info/top_level.txt
graphyne-1.2.2.dist-info/RECORD
